dictionary/__init__.py
dictionary/dictionary.py
turan_mert_duran_dictionary_hw1-2.0.0.dist-info/METADATA
turan_mert_duran_dictionary_hw1-2.0.0.dist-info/WHEEL
turan_mert_duran_dictionary_hw1-2.0.0.dist-info/top_level.txt
turan_mert_duran_dictionary_hw1-2.0.0.dist-info/RECORD
