Metadata-Version: 2.1
Name: turan-mert-duran-dictionary-hw1
Version: 2.0.0
Summary: UNKNOWN
Author: Turan Mert Duran
License: UNKNOWN
Platform: UNKNOWN
Requires-Python: >=3.8
Requires-Dist: requests (>=2.23.0)
